optimizer/__init__.py
patatune/__init__.py
patatune/metrics.py
patatune/objective.py
patatune/optimizer.py
patatune/util.py
patatune/mopso/__init__.py
patatune/mopso/mopso.py
patatune/mopso/particle.py
patatune-1.0.3.dist-info/licenses/LICENSE
patatune-1.0.3.dist-info/METADATA
patatune-1.0.3.dist-info/WHEEL
patatune-1.0.3.dist-info/top_level.txt
patatune-1.0.3.dist-info/RECORD
