Metadata-Version: 2.4
Name: patatune
Version: 1.0.3
Summary: A optimization library for multi-objective optimization problems.
Project-URL: Source Code, https://github.com/cms-patatrack/patatune
Project-URL: Issues, https://github.com/cms-patatrack/patatune/issues
Classifier: Programming Language :: Python :: 3
Classifier: Operating System :: OS Independent
Classifier: License :: OSI Approved :: Mozilla Public License 2.0 (MPL 2.0)
License-File: LICENSE
Requires-Dist: numpy
Requires-Dist: dill
Provides-Extra: numba
Requires-Dist: numba; extra == "numba"
Provides-Extra: zarr
Requires-Dist: zarr==2.*; extra == "zarr"
Provides-Extra: tests
Requires-Dist: pandas; extra == "tests"
Requires-Dist: matplotlib; extra == "tests"
Provides-Extra: extra
Requires-Dist: numba; extra == "extra"
Requires-Dist: zarr==2.*; extra == "extra"
Provides-Extra: all
Requires-Dist: numba; extra == "all"
Requires-Dist: zarr==2.*; extra == "all"
Requires-Dist: pandas; extra == "all"
Requires-Dist: matplotlib; extra == "all"
Dynamic: license-file
